{
    "brand_name": "RRL",
    "colors": [
        "Service Navy"
    ],
    "description": "Classic-fitting pants with a straight leg and a high rise. Made from Japanese cotton twill. Washed for softness.",
    "fitting_details": [
        "Classic fit with a straight leg and a high rise.",
        "Size 32W has a 12\u00bc\" rise and an 18\u00bd\" leg opening.",
        "Belt loops. Button fly with a buttoned closure.",
        "Two front angled pockets. Right hip coin pocket. Back right buttoned pocket. Back left welt pocket.",
        "100% cotton.",
        "Machine washable.",
        "Imported."
    ],
    "img_links": [
        "https://www.rlmedia.io/is/image/PoloGSI/s7-1407119_lifestyle?$rl_pdp_mob_zoom$",
        "https://www.rlmedia.io/is/image/PoloGSI/s7-1407119_alternate1?$rl_pdp_mob_zoom$",
        "https://www.rlmedia.io/is/image/PoloGSI/s7-1407119_alternate20?$rl_pdp_mob_zoom$"
    ],
    "price": "$240.00",
    "product": "Chino Field Pant",
    "product_id": "577056",
    "sizes": [
        "26",
        "27",
        "28",
        "29",
        "30",
        "31",
        "32",
        "33",
        "34",
        "35",
        "36",
        "38",
        "40",
        "42",
        "30",
        "32",
        "34"
    ],
    "video_links": []
}