{
    "brand_name": "Big & Tall",
    "colors": [
        "Vintage Khaki",
        "BIG 1X",
        "BIG 2X",
        "BIG 3X",
        "BIG 4X",
        "BIG 5X",
        "BIG 6X",
        "TALL L",
        "TALL XL",
        "TALL 2L",
        "TALL 3L",
        "TALL 4L",
        "TALL 5L"
    ],
    "description": "With an elastic drawstring waist and a roomy fit, these lightweight pants draw inspiration from our signature Polo Prepster shorts.",
    "fitting_details": [
        "Stretch Classic Fit: sits at the waist. Eased through the leg.",
        "Size Big 2X has 43\" waist that expands to 50\", a 12\u00bd\" rise, and a 28\" inseam.",
        "Size Tall 2L has 43\" waist that expands to 50\", a 12\u00bd\" rise, and a 32\" inseam.",
        "Elastic waistband with an interior drawstring. Zip fly with a buttoned closure.",
        "Two front angled pockets. Two back buttoned pockets.",
        "Signature embroidered Pony above the back right pocket.",
        "Cotton, elastane.",
        "Machine washable.",
        "Imported."
    ],
    "img_links": [
        "https://www.rlmedia.io/is/image/PoloGSI/s7-1411474_alternate10?$rl_pdp_mob_zoom$",
        "https://www.rlmedia.io/is/image/PoloGSI/s7-1411474_lifestyle?$rl_pdp_mob_zoom$",
        "https://www.rlmedia.io/is/image/PoloGSI/s7-1411474_alternate1?$rl_pdp_mob_zoom$",
        "https://www.rlmedia.io/is/image/PoloGSI/s7-1411474_alternate3?$rl_pdp_mob_zoom$",
        "https://www.rlmedia.io/is/image/PoloGSI/s7-1411474_alternate4?$rl_pdp_mob_zoom$"
    ],
    "price": "$89.50",
    "product": "Polo Prepster Stretch Chino Pant",
    "product_id": "583331",
    "sizes": [
        "1X"
    ],
    "video_links": [
        "https://www.rlmedia.io/is/content/PoloGSI/s7-1411474_rlvideo_vid?video_desktop"
    ]
}