{
    "brand_name": "Big & Tall",
    "colors": [
        "Andrew Stripe/Cruise Navy",
        "2L Tall",
        "3L Tall",
        "4L Tall"
    ],
    "description": "These pajama pants are made from striped cotton broadcloth and feature our signature embroidered Pony at the left hip.",
    "fitting_details": [
        "Size Big 2X has a 30\u00bd\" inseam.",
        "Size Tall 2L has a 32\u00bd\" inseam.",
        "Covered elastic drawstring waistband with a signature \"Polo Ralph Lauren\" label at the center front.",
        "Single-button fly.",
        "Two side on-seam pockets.",
        "Signature embroidered Pony at the left hip.",
        "100% cotton.",
        "Machine washable.",
        "Imported."
    ],
    "img_links": [
        "https://www.rlmedia.io/is/image/PoloGSI/s7-1368419_lifestyle?$rl_pdp_mob_zoom$",
        "https://www.rlmedia.io/is/image/PoloGSI/s7-1368419_alternate1?$rl_pdp_mob_zoom$",
        "https://www.rlmedia.io/is/image/PoloGSI/s7-1368419_alternate2?$rl_pdp_mob_zoom$",
        "https://www.rlmedia.io/is/image/PoloGSI/s7-1368419_alternate3?$rl_pdp_mob_zoom$",
        "https://www.rlmedia.io/is/image/PoloGSI/s7-1368419_alternate4?$rl_pdp_mob_zoom$"
    ],
    "price": "$59.50",
    "product": "Striped Cotton Pajama Pant",
    "product_id": "530540",
    "sizes": [
        "1X Big",
        "2X Big",
        "3X Big",
        "4X Big",
        "XL Tall"
    ],
    "video_links": []
}