{
    "brand_name": "Big & Tall",
    "colors": [
        "Polo Black",
        "Jamaica Heather"
    ],
    "description": "This version of our signature button-down is cut from an ultrathin layer of our most lightweight cotton mesh, making it the perfect shirt for transitional days or when you want a comfortable layer underneath sweaters or jackets.",
    "fitting_details": [
        "Size Big 2X has a 32\" body length, a 22\" shoulder, a 28\" chest, and a 36\u00bd\" sleeve length. Sleeve length is taken from the center back of the neck and changes \u00be\" between sizes.",
        "Size Tall 2L has a 35\" body length, a 22\" shoulder, a 28\" chest, and a 38\u00bd\" sleeve length. Sleeve length is taken from the center back of the neck and changes \u00be\" between sizes.",
        "Button-down point collar. Buttoned placket.",
        "Long sleeves with buttoned barrel cuffs.",
        "Split back yoke with a box pleat ensures a comfortable fit and a greater range of motion.",
        "Signature embroidered pony at the left chest.",
        "Cotton.",
        "Machine washable.",
        "Imported."
    ],
    "img_links": [
        "https://www.rlmedia.io/is/image/PoloGSI/s7-1331460_alternate10?$rl_pdp_mob_zoom$",
        "https://www.rlmedia.io/is/image/PoloGSI/s7-1331460_lifestyle?$rl_pdp_mob_zoom$",
        "https://www.rlmedia.io/is/image/PoloGSI/s7-1331460_alternate1?$rl_pdp_mob_zoom$",
        "https://www.rlmedia.io/is/image/PoloGSI/s7-1331460_alternate2?$rl_pdp_mob_zoom$",
        "https://www.rlmedia.io/is/image/PoloGSI/s7-1331460_alternate3?$rl_pdp_mob_zoom$",
        "https://www.rlmedia.io/is/image/PoloGSI/s7-1331460_alternate4?$rl_pdp_mob_zoom$",
        "https://www.rlmedia.io/is/image/PoloGSI/s7-1331460_alternate20?$rl_pdp_mob_zoom$"
    ],
    "price": "$98.50",
    "product": "Featherweight Mesh Shirt",
    "product_id": "467858",
    "sizes": [
        "1X",
        "1X Big",
        "2X Big",
        "3X Big",
        "4X Big",
        "5X Big",
        "6X Big",
        "L Tall",
        "XL Tall",
        "2XL Tall",
        "3XL Tall",
        "4XL Tall",
        "5XL Tall"
    ],
    "video_links": [
        "https://www.rlmedia.io/is/content/PoloGSI/s7-1331460_rlvideo_vid?video_desktop"
    ]
}