{
    "brand_name": "Polo Ralph Lauren",
    "colors": [
        "Black And Cream"
    ],
    "description": "Created to mark the 50th anniversary of Ralph Lauren, the RL67 jacket draws inspiration from a herringbone sport coat that has been a treasured part of Mr. Lauren's wardrobe since 1971. This reinterpretation is made in America from a black-and-white wool tweed that was developed exclusively for Polo by a storied Irish mill.",
    "fitting_details": [
        "Trim fit, with a soft shoulder, a high armhole, 4\" lapels, and a shorter length.",
        "Size 40R jacket has a 30\" front body length, a 29\u00bd\" back body length, an 18\u00bd\" shoulder, and a 17\u00bd\" sleeve inseam.",
        "Notch lapels. Buttoned throat latch. Black Watch undercollar. Two-button silhouette.",
        "Suede elbow patches. Cuffs with four decorative buttons.",
        "Left chest welt pocket. Two front waist flapped pockets. Two interior chest pockets. Interior left waist welt pocket.",
        "Double vent. Half-canvassed. Fully lined.",
        "Alterations available in Ralph Lauren retail stores.",
        "Shell: lambswool, alpaca wool. Body lining: cupro. Sleeve lining: viscose. Dry clean. Made in USA. Imported fabric.",
        "Model is 6'1\"/185 cm and wears a size 40R."
    ],
    "img_links": [
        "https://www.rlmedia.io/is/image/PoloGSI/s7-1302455_alternate10?$rl_pdp_mob_zoom$",
        "https://www.rlmedia.io/is/image/PoloGSI/s7-1302455_lifestyle?$rl_pdp_mob_zoom$",
        "https://www.rlmedia.io/is/image/PoloGSI/s7-1302455_alternate1?$rl_pdp_mob_zoom$",
        "https://www.rlmedia.io/is/image/PoloGSI/s7-1302455_alternate2?$rl_pdp_mob_zoom$",
        "https://www.rlmedia.io/is/image/PoloGSI/s7-1302455_alternate3?$rl_pdp_mob_zoom$",
        "https://www.rlmedia.io/is/image/PoloGSI/s7-1302455_alternate4?$rl_pdp_mob_zoom$",
        "https://www.rlmedia.io/is/image/PoloGSI/s7-1302455_alternate5?$rl_pdp_mob_zoom$"
    ],
    "price": "$1,198.00",
    "product": "The RL67 Jacket",
    "product_id": "445346",
    "sizes": [
        "32",
        "34",
        "36",
        "38",
        "40",
        "42",
        "44",
        "46",
        "48",
        "50",
        "52",
        "54",
        "Short",
        "Regular",
        "Long"
    ],
    "video_links": [
        "https://www.rlmedia.io/is/content/PoloGSI/s7-1302455_rlvideo_vid?video_desktop"
    ]
}